py_ssd-0.20.1.dist-info/METADATA
py_ssd-0.20.1.dist-info/WHEEL
py_ssd-0.20.1.dist-info/license_files/LICENSE
py_ssd-0.20.1.dist-info/license_files/LICENSE
py_ssd/__init__.py
py_ssd/py_ssd.cpython-311-s390x-linux-gnu.so
py_ssd-0.20.1.dist-info/RECORD
