Metadata-Version: 2.3
Name: py_ssd
Version: 0.20.1
Classifier: Programming Language :: Rust
Classifier: Programming Language :: Python :: Implementation :: CPython
Classifier: Programming Language :: Python :: Implementation :: PyPy
License-File: LICENSE
License-File: LICENSE
Summary: A service and data description format + a code generator based on rhai scripts and templates
Home-Page: https://github.com/ssd-codegen/ssd
Requires-Python: >=3.8
Project-URL: Source Code, https://github.com/ssd-codegen/ssd
